[
  {
    "id": "1751727928321k8zyf2n4j",
    "userId": "1751033764233vfurc86wp",
    "dailyStats": [
      {
        "date": "2025-04-07",
        "notesCreated": 0,
        "flashcardsStudied": 0,
        "flashcardsCreated": 0,
        "createdAt": "2025-07-05T15:30:46.052Z"
      },
      {
        "date": "2025-04-08",
        "notesCreated": 0,
        "flashcardsStudied": 0,
        "flashcardsCreated": 0,
        "createdAt": "2025-07-05T15:30:46.052Z"
      },
      {
        "date": "2025-04-09",
        "notesCreated": 0,
        "flashcardsStudied": 0,
        "flashcardsCreated": 0,
        "createdAt": "2025-07-05T15:30:46.052Z"
      },
      {
        "date": "2025-04-10",
        "notesCreated": 0,
        "flashcardsStudied": 0,
        "flashcardsCreated": 0,
        "createdAt": "2025-07-05T15:30:46.052Z"
      },
      {
        "date": "2025-04-11",
        "notesCreated": 0,
        "flashcardsStudied": 0,
        "flashcardsCreated": 0,
        "createdAt": "2025-07-05T15:30:46.052Z"
      },
      {
        "date": "2025-04-12",
        "notesCreated": 0,
        "flashcardsStudied": 0,
        "flashcardsCreated": 0,
        "createdAt": "2025-07-05T15:30:46.052Z"
      },
      {
        "date": "2025-04-13",
        "notesCreated": 0,
        "flashcardsStudied": 0,
        "flashcardsCreated": 0,
        "createdAt": "2025-07-05T15:30:46.052Z"
      },
      {
        "date": "2025-04-14",
        "notesCreated": 0,
        "flashcardsStudied": 0,
        "flashcardsCreated": 0,
        "createdAt": "2025-07-05T15:30:46.052Z"
      },
      {
        "date": "2025-04-15",
        "notesCreated": 0,
        "flashcardsStudied": 0,
        "flashcardsCreated": 0,
        "createdAt": "2025-07-05T15:30:46.052Z"
      },
      {
        "date": "2025-04-16",
        "notesCreated": 0,
        "flashcardsStudied": 0,
        "flashcardsCreated": 0,
        "createdAt": "2025-07-05T15:30:46.052Z"
      },
      {
        "date": "2025-04-17",
        "notesCreated": 0,
        "flashcardsStudied": 0,
        "flashcardsCreated": 0,
        "createdAt": "2025-07-05T15:30:46.052Z"
      },
      {
        "date": "2025-04-18",
        "notesCreated": 0,
        "flashcardsStudied": 0,
        "flashcardsCreated": 0,
        "createdAt": "2025-07-05T15:30:46.052Z"
      },
      {
        "date": "2025-04-19",
        "notesCreated": 0,
        "flashcardsStudied": 0,
        "flashcardsCreated": 0,
        "createdAt": "2025-07-05T15:30:46.052Z"
      },
      {
        "date": "2025-04-20",
        "notesCreated": 0,
        "flashcardsStudied": 0,
        "flashcardsCreated": 0,
        "createdAt": "2025-07-05T15:30:46.052Z"
      },
      {
        "date": "2025-04-21",
        "notesCreated": 0,
        "flashcardsStudied": 0,
        "flashcardsCreated": 0,
        "createdAt": "2025-07-05T15:30:46.052Z"
      },
      {
        "date": "2025-04-22",
        "notesCreated": 0,
        "flashcardsStudied": 0,
        "flashcardsCreated": 0,
        "createdAt": "2025-07-05T15:30:46.052Z"
      },
      {
        "date": "2025-04-23",
        "notesCreated": 0,
        "flashcardsStudied": 0,
        "flashcardsCreated": 0,
        "createdAt": "2025-07-05T15:30:46.052Z"
      },
      {
        "date": "2025-04-24",
        "notesCreated": 0,
        "flashcardsStudied": 0,
        "flashcardsCreated": 0,
        "createdAt": "2025-07-05T15:30:46.052Z"
      },
      {
        "date": "2025-04-25",
        "notesCreated": 0,
        "flashcardsStudied": 0,
        "flashcardsCreated": 0,
        "createdAt": "2025-07-05T15:30:46.052Z"
      },
      {
        "date": "2025-04-26",
        "notesCreated": 0,
        "flashcardsStudied": 0,
        "flashcardsCreated": 0,
        "createdAt": "2025-07-05T15:30:46.052Z"
      },
      {
        "date": "2025-04-27",
        "notesCreated": 0,
        "flashcardsStudied": 0,
        "flashcardsCreated": 0,
        "createdAt": "2025-07-05T15:30:46.052Z"
      },
      {
        "date": "2025-04-28",
        "notesCreated": 0,
        "flashcardsStudied": 0,
        "flashcardsCreated": 0,
        "createdAt": "2025-07-05T15:30:46.052Z"
      },
      {
        "date": "2025-04-29",
        "notesCreated": 0,
        "flashcardsStudied": 0,
        "flashcardsCreated": 0,
        "createdAt": "2025-07-05T15:30:46.052Z"
      },
      {
        "date": "2025-04-30",
        "notesCreated": 0,
        "flashcardsStudied": 0,
        "flashcardsCreated": 0,
        "createdAt": "2025-07-05T15:30:46.052Z"
      },
      {
        "date": "2025-05-01",
        "notesCreated": 0,
        "flashcardsStudied": 0,
        "flashcardsCreated": 0,
        "createdAt": "2025-07-05T15:30:46.052Z"
      },
      {
        "date": "2025-05-02",
        "notesCreated": 0,
        "flashcardsStudied": 0,
        "flashcardsCreated": 0,
        "createdAt": "2025-07-05T15:30:46.052Z"
      },
      {
        "date": "2025-05-03",
        "notesCreated": 0,
        "flashcardsStudied": 0,
        "flashcardsCreated": 0,
        "createdAt": "2025-07-05T15:30:46.052Z"
      },
      {
        "date": "2025-05-04",
        "notesCreated": 0,
        "flashcardsStudied": 0,
        "flashcardsCreated": 0,
        "createdAt": "2025-07-05T15:30:46.052Z"
      },
      {
        "date": "2025-05-05",
        "notesCreated": 0,
        "flashcardsStudied": 0,
        "flashcardsCreated": 0,
        "createdAt": "2025-07-05T15:30:46.052Z"
      },
      {
        "date": "2025-05-06",
        "notesCreated": 0,
        "flashcardsStudied": 0,
        "flashcardsCreated": 0,
        "createdAt": "2025-07-05T15:30:46.052Z"
      },
      {
        "date": "2025-05-07",
        "notesCreated": 0,
        "flashcardsStudied": 0,
        "flashcardsCreated": 0,
        "createdAt": "2025-07-05T15:30:46.052Z"
      },
      {
        "date": "2025-05-08",
        "notesCreated": 0,
        "flashcardsStudied": 0,
        "flashcardsCreated": 0,
        "createdAt": "2025-07-05T15:30:46.052Z"
      },
      {
        "date": "2025-05-09",
        "notesCreated": 0,
        "flashcardsStudied": 0,
        "flashcardsCreated": 0,
        "createdAt": "2025-07-05T15:30:46.052Z"
      },
      {
        "date": "2025-05-10",
        "notesCreated": 0,
        "flashcardsStudied": 0,
        "flashcardsCreated": 0,
        "createdAt": "2025-07-05T15:30:46.052Z"
      },
      {
        "date": "2025-05-11",
        "notesCreated": 0,
        "flashcardsStudied": 0,
        "flashcardsCreated": 0,
        "createdAt": "2025-07-05T15:30:46.052Z"
      },
      {
        "date": "2025-05-12",
        "notesCreated": 0,
        "flashcardsStudied": 0,
        "flashcardsCreated": 0,
        "createdAt": "2025-07-05T15:30:46.052Z"
      },
      {
        "date": "2025-05-13",
        "notesCreated": 0,
        "flashcardsStudied": 0,
        "flashcardsCreated": 0,
        "createdAt": "2025-07-05T15:30:46.052Z"
      },
      {
        "date": "2025-05-14",
        "notesCreated": 0,
        "flashcardsStudied": 0,
        "flashcardsCreated": 0,
        "createdAt": "2025-07-05T15:30:46.052Z"
      },
      {
        "date": "2025-05-15",
        "notesCreated": 0,
        "flashcardsStudied": 0,
        "flashcardsCreated": 0,
        "createdAt": "2025-07-05T15:30:46.052Z"
      },
      {
        "date": "2025-05-16",
        "notesCreated": 0,
        "flashcardsStudied": 0,
        "flashcardsCreated": 0,
        "createdAt": "2025-07-05T15:30:46.052Z"
      },
      {
        "date": "2025-05-17",
        "notesCreated": 0,
        "flashcardsStudied": 0,
        "flashcardsCreated": 0,
        "createdAt": "2025-07-05T15:30:46.052Z"
      },
      {
        "date": "2025-05-18",
        "notesCreated": 0,
        "flashcardsStudied": 0,
        "flashcardsCreated": 0,
        "createdAt": "2025-07-05T15:30:46.052Z"
      },
      {
        "date": "2025-05-19",
        "notesCreated": 0,
        "flashcardsStudied": 0,
        "flashcardsCreated": 0,
        "createdAt": "2025-07-05T15:30:46.052Z"
      },
      {
        "date": "2025-05-20",
        "notesCreated": 0,
        "flashcardsStudied": 0,
        "flashcardsCreated": 0,
        "createdAt": "2025-07-05T15:30:46.052Z"
      },
      {
        "date": "2025-05-21",
        "notesCreated": 0,
        "flashcardsStudied": 0,
        "flashcardsCreated": 0,
        "createdAt": "2025-07-05T15:30:46.052Z"
      },
      {
        "date": "2025-05-22",
        "notesCreated": 0,
        "flashcardsStudied": 0,
        "flashcardsCreated": 0,
        "createdAt": "2025-07-05T15:30:46.052Z"
      },
      {
        "date": "2025-05-23",
        "notesCreated": 0,
        "flashcardsStudied": 0,
        "flashcardsCreated": 0,
        "createdAt": "2025-07-05T15:30:46.052Z"
      },
      {
        "date": "2025-05-24",
        "notesCreated": 0,
        "flashcardsStudied": 0,
        "flashcardsCreated": 0,
        "createdAt": "2025-07-05T15:30:46.052Z"
      },
      {
        "date": "2025-05-25",
        "notesCreated": 0,
        "flashcardsStudied": 0,
        "flashcardsCreated": 0,
        "createdAt": "2025-07-05T15:30:46.052Z"
      },
      {
        "date": "2025-05-26",
        "notesCreated": 0,
        "flashcardsStudied": 0,
        "flashcardsCreated": 0,
        "createdAt": "2025-07-05T15:30:46.052Z"
      },
      {
        "date": "2025-05-27",
        "notesCreated": 0,
        "flashcardsStudied": 0,
        "flashcardsCreated": 0,
        "createdAt": "2025-07-05T15:30:46.052Z"
      },
      {
        "date": "2025-05-28",
        "notesCreated": 0,
        "flashcardsStudied": 0,
        "flashcardsCreated": 0,
        "createdAt": "2025-07-05T15:30:46.052Z"
      },
      {
        "date": "2025-05-29",
        "notesCreated": 0,
        "flashcardsStudied": 0,
        "flashcardsCreated": 0,
        "createdAt": "2025-07-05T15:30:46.052Z"
      },
      {
        "date": "2025-05-30",
        "notesCreated": 0,
        "flashcardsStudied": 0,
        "flashcardsCreated": 0,
        "createdAt": "2025-07-05T15:30:46.052Z"
      },
      {
        "date": "2025-05-31",
        "notesCreated": 0,
        "flashcardsStudied": 0,
        "flashcardsCreated": 0,
        "createdAt": "2025-07-05T15:30:46.052Z"
      },
      {
        "date": "2025-06-01",
        "notesCreated": 0,
        "flashcardsStudied": 0,
        "flashcardsCreated": 0,
        "createdAt": "2025-07-05T15:30:46.052Z"
      },
      {
        "date": "2025-06-02",
        "notesCreated": 0,
        "flashcardsStudied": 0,
        "flashcardsCreated": 0,
        "createdAt": "2025-07-05T15:30:46.052Z"
      },
      {
        "date": "2025-06-03",
        "notesCreated": 0,
        "flashcardsStudied": 0,
        "flashcardsCreated": 0,
        "createdAt": "2025-07-05T15:30:46.052Z"
      },
      {
        "date": "2025-06-04",
        "notesCreated": 0,
        "flashcardsStudied": 0,
        "flashcardsCreated": 0,
        "createdAt": "2025-07-05T15:30:46.052Z"
      },
      {
        "date": "2025-06-05",
        "notesCreated": 0,
        "flashcardsStudied": 0,
        "flashcardsCreated": 0,
        "createdAt": "2025-07-05T15:30:46.052Z"
      },
      {
        "date": "2025-06-06",
        "notesCreated": 0,
        "flashcardsStudied": 0,
        "flashcardsCreated": 0,
        "createdAt": "2025-07-05T15:30:46.052Z"
      },
      {
        "date": "2025-06-07",
        "notesCreated": 0,
        "flashcardsStudied": 0,
        "flashcardsCreated": 0,
        "createdAt": "2025-07-05T15:30:46.052Z"
      },
      {
        "date": "2025-06-08",
        "notesCreated": 0,
        "flashcardsStudied": 0,
        "flashcardsCreated": 0,
        "createdAt": "2025-07-05T15:30:46.052Z"
      },
      {
        "date": "2025-06-09",
        "notesCreated": 0,
        "flashcardsStudied": 0,
        "flashcardsCreated": 0,
        "createdAt": "2025-07-05T15:30:46.052Z"
      },
      {
        "date": "2025-06-10",
        "notesCreated": 0,
        "flashcardsStudied": 0,
        "flashcardsCreated": 0,
        "createdAt": "2025-07-05T15:30:46.052Z"
      },
      {
        "date": "2025-06-11",
        "notesCreated": 0,
        "flashcardsStudied": 0,
        "flashcardsCreated": 0,
        "createdAt": "2025-07-05T15:30:46.052Z"
      },
      {
        "date": "2025-06-12",
        "notesCreated": 0,
        "flashcardsStudied": 0,
        "flashcardsCreated": 0,
        "createdAt": "2025-07-05T15:30:46.052Z"
      },
      {
        "date": "2025-06-13",
        "notesCreated": 0,
        "flashcardsStudied": 0,
        "flashcardsCreated": 0,
        "createdAt": "2025-07-05T15:30:46.052Z"
      },
      {
        "date": "2025-06-14",
        "notesCreated": 0,
        "flashcardsStudied": 0,
        "flashcardsCreated": 0,
        "createdAt": "2025-07-05T15:30:46.052Z"
      },
      {
        "date": "2025-06-15",
        "notesCreated": 0,
        "flashcardsStudied": 0,
        "flashcardsCreated": 0,
        "createdAt": "2025-07-05T15:30:46.052Z"
      },
      {
        "date": "2025-06-16",
        "notesCreated": 0,
        "flashcardsStudied": 0,
        "flashcardsCreated": 0,
        "createdAt": "2025-07-05T15:30:46.052Z"
      },
      {
        "date": "2025-06-17",
        "notesCreated": 0,
        "flashcardsStudied": 0,
        "flashcardsCreated": 0,
        "createdAt": "2025-07-05T15:30:46.052Z"
      },
      {
        "date": "2025-06-18",
        "notesCreated": 0,
        "flashcardsStudied": 0,
        "flashcardsCreated": 0,
        "createdAt": "2025-07-05T15:30:46.052Z"
      },
      {
        "date": "2025-06-19",
        "notesCreated": 0,
        "flashcardsStudied": 0,
        "flashcardsCreated": 0,
        "createdAt": "2025-07-05T15:30:46.052Z"
      },
      {
        "date": "2025-06-20",
        "notesCreated": 0,
        "flashcardsStudied": 0,
        "flashcardsCreated": 0,
        "createdAt": "2025-07-05T15:30:46.052Z"
      },
      {
        "date": "2025-06-21",
        "notesCreated": 0,
        "flashcardsStudied": 0,
        "flashcardsCreated": 0,
        "createdAt": "2025-07-05T15:30:46.052Z"
      },
      {
        "date": "2025-06-22",
        "notesCreated": 0,
        "flashcardsStudied": 0,
        "flashcardsCreated": 0,
        "createdAt": "2025-07-05T15:30:46.052Z"
      },
      {
        "date": "2025-06-23",
        "notesCreated": 0,
        "flashcardsStudied": 0,
        "flashcardsCreated": 0,
        "createdAt": "2025-07-05T15:30:46.052Z"
      },
      {
        "date": "2025-06-24",
        "notesCreated": 0,
        "flashcardsStudied": 0,
        "flashcardsCreated": 0,
        "createdAt": "2025-07-05T15:30:46.052Z"
      },
      {
        "date": "2025-06-25",
        "notesCreated": 0,
        "flashcardsStudied": 0,
        "flashcardsCreated": 0,
        "createdAt": "2025-07-05T15:30:46.052Z"
      },
      {
        "date": "2025-06-26",
        "notesCreated": 0,
        "flashcardsStudied": 0,
        "flashcardsCreated": 0,
        "createdAt": "2025-07-05T15:30:46.052Z"
      },
      {
        "date": "2025-06-27",
        "notesCreated": 0,
        "flashcardsStudied": 0,
        "flashcardsCreated": 0,
        "createdAt": "2025-07-05T15:30:46.052Z"
      },
      {
        "date": "2025-06-28",
        "notesCreated": 1,
        "flashcardsStudied": 0,
        "flashcardsCreated": 0,
        "createdAt": "2025-07-05T15:30:46.052Z"
      },
      {
        "date": "2025-06-29",
        "notesCreated": 1,
        "flashcardsStudied": 0,
        "flashcardsCreated": 0,
        "createdAt": "2025-07-05T15:30:46.052Z"
      },
      {
        "date": "2025-06-30",
        "notesCreated": 0,
        "flashcardsStudied": 0,
        "flashcardsCreated": 0,
        "createdAt": "2025-07-05T15:30:46.052Z"
      },
      {
        "date": "2025-07-01",
        "notesCreated": 0,
        "flashcardsStudied": 0,
        "flashcardsCreated": 0,
        "createdAt": "2025-07-05T15:30:46.052Z"
      },
      {
        "date": "2025-07-02",
        "notesCreated": 0,
        "flashcardsStudied": 0,
        "flashcardsCreated": 0,
        "createdAt": "2025-07-05T15:30:46.052Z"
      },
      {
        "date": "2025-07-03",
        "notesCreated": 0,
        "flashcardsStudied": 0,
        "flashcardsCreated": 0,
        "createdAt": "2025-07-05T15:30:46.052Z"
      },
      {
        "date": "2025-07-04",
        "notesCreated": 0,
        "flashcardsStudied": 0,
        "flashcardsCreated": 0,
        "createdAt": "2025-07-05T15:30:46.052Z"
      },
      {
        "date": "2025-07-05",
        "notesCreated": 0,
        "flashcardsStudied": 11,
        "flashcardsCreated": 6,
        "createdAt": "2025-07-05T15:30:46.052Z"
      }
    ],
    "createdAt": "2025-07-05T15:05:28.321Z",
    "updatedAt": "2025-07-05T16:02:13.356Z"
  },
  {
    "id": "1752075490504zjzmny65n",
    "userId": "test-user-123",
    "dailyStats": [
      {
        "date": "2025-07-09",
        "notesCreated": 1,
        "flashcardsStudied": 0,
        "flashcardsCreated": 0,
        "createdAt": "2025-07-09T15:38:10.505Z"
      }
    ],
    "createdAt": "2025-07-09T15:38:10.504Z",
    "updatedAt": "2025-07-09T15:38:10.505Z"
  }
]